{
	"animations": [
		{
			"offsets": [
				0,
				0
			],
			"indices": [],
			"fps": 24,
			"anim": "idle",
			"loop": false,
			"name": "json idle"
		},
		{
			"offsets": [
				66,
				-2
			],
			"indices": [],
			"fps": 24,
			"anim": "singLEFT",
			"loop": false,
			"name": "json left"
		},
		{
			"offsets": [
				-21,
				-102
			],
			"indices": [],
			"fps": 24,
			"anim": "singDOWN",
			"loop": false,
			"name": "json down"
		},
		{
			"offsets": [
				-15,
				32
			],
			"indices": [],
			"fps": 24,
			"anim": "singUP",
			"loop": false,
			"name": "json up"
		},
		{
			"offsets": [
				-27,
				-36
			],
			"indices": [],
			"fps": 24,
			"anim": "singRIGHT",
			"loop": false,
			"name": "json right"
		}
	],
	"vocals_file": "",
	"no_antialiasing": false,
	"image": "characters/gameboy_bozo",
	"position": [
		90,
		100
	],
	"healthicon": "gb",
	"flip_x": false,
	"camera_position": [
		0,
		0
	],
	"sing_duration": 4,
	"scale": 1,
	"_editor_isPlayer": false
}