{
	"songs": [
		[
			"An-eble",
			"bozo",
			[
				206,
				77,
				63
			],
			"volume2"
		],
		[
			"Lame (Old)",
			"bozo",
			[
				206,
				77,
				63
			],
			"volume2"
		],
		[
			"Deestroyer (Old)",
			"dees",
			[
				82,
				154,
				149
			],
			"volume2"
		]
	],
	"weekCharacters": [
		"",
		"",
		""
	],
	"weekBackground": "",
	"weekBefore": "",
	"storyName": "",
	"weekName": "Bozo Week Old",
	"startUnlocked": true,
	"hiddenUntilUnlocked": false,
	"hideStoryMode": true,
	"hideFreeplay": false,
	"difficulties": "Normal",
	"album": "old"
}